pipecat_respeecher/__init__.py
pipecat_respeecher/tts.py
pipecat_respeecher-0.1.2.dist-info/licenses/LICENSE
pipecat_respeecher-0.1.2.dist-info/METADATA
pipecat_respeecher-0.1.2.dist-info/WHEEL
pipecat_respeecher-0.1.2.dist-info/top_level.txt
pipecat_respeecher-0.1.2.dist-info/RECORD
