Metadata-Version: 2.4
Name: pipecat-respeecher
Version: 0.1.2
Summary: Respeecher real-time TTS plugin for Pipecat
Author-email: Respeecher <nv@respeecher.com>
Maintainer-email: Respeecher <nv@respeecher.com>
License-Expression: BSD-2-Clause
Project-URL: Homepage, https://www.respeecher.com/real-time-tts-api
Project-URL: Documentation, https://space.respeecher.com/docs
Project-URL: Source, https://github.com/respeecher/pipecat-respeecher
Project-URL: Changelog, https://github.com/respeecher/pipecat-respeecher/blob/main/CHANGELOG.md
Keywords: tts,pipecat-ai,pipecat
Classifier: Intended Audience :: Developers
Classifier: Operating System :: OS Independent
Classifier: Programming Language :: Python :: 3.10
Classifier: Programming Language :: Python :: 3.11
Classifier: Programming Language :: Python :: 3.12
Classifier: Programming Language :: Python :: 3.13
Classifier: Topic :: Software Development :: Libraries :: Python Modules
Requires-Python: >=3.10
License-File: LICENSE
Requires-Dist: pipecat-ai>=0.0.99
Requires-Dist: respeecher>=1.1.9
Dynamic: license-file
